pytextractor/__init__.py
pytextractor/pytextractor.py
pytextractor/text_detection.py
tests/__init__.py
tests/test_detector.py
pytextractor-2.1.0.dist-info/LICENSE
pytextractor-2.1.0.dist-info/METADATA
pytextractor-2.1.0.dist-info/WHEEL
pytextractor-2.1.0.dist-info/entry_points.txt
pytextractor-2.1.0.dist-info/top_level.txt
pytextractor-2.1.0.dist-info/RECORD
