Metadata-Version: 2.1
Name: pytextractor
Version: 2.1.0
Summary: text extractor from images
Home-page: https://github.com/danwald/pytextractor/
Author: danny crasto
Author-email: danwald79@gmail.com
License: MIT
Classifier: License :: OSI Approved :: MIT License
Classifier: Programming Language :: Python
Classifier: Programming Language :: Python :: 3
Classifier: Programming Language :: Python :: 3.9
Classifier: Programming Language :: Python :: 3.10
Classifier: Programming Language :: Python :: 3.11
Classifier: Programming Language :: Python :: 3.12
Classifier: License :: OSI Approved :: MIT License
License-File: LICENSE
Requires-Dist: imutils
Requires-Dist: opencv-python
Requires-Dist: Pillow
Requires-Dist: pytesseract
Requires-Dist: requests
Requires-Dist: setuptools
Provides-Extra: dev
Requires-Dist: pytest ; extra == 'dev'
